sei_json_rpc/__init__.py
sei_json_rpc/cases/eth/get_balance.yml
sei_json_rpc/cases/eth/get_block.yml
sei_json_rpc/cases/eth/get_block_receipts.yml
sei_json_rpc/cases/eth/get_code.yml
sei_json_rpc/cases/eth/get_proof.yml
sei_json_rpc/cases/eth/get_storage_at.yml
sei_json_rpc/cases/eth/get_transaction.yml
sei_json_rpc/cases/eth/get_transaction_by_block.yml
sei_json_rpc/cases/eth/get_transaction_count.yml
sei_json_rpc/cases/eth/get_transaction_receipt.yml
sei_json_rpc/cases/sei/get_balance.yml
sei_json_rpc/cases/sei/get_transaction_by_block_number.yml
sei_json_rpc/cases/sei/get_transaction_receipt.yml
sei_json_rpc/core/__init__.py
sei_json_rpc/core/client_manager.py
sei_json_rpc/core/models.py
sei_json_rpc/core/rpc_tester.py
sei_json_rpc/main.py
sei_json_rpc/tests/conftest.py
sei_json_rpc/tests/contract/ERC20.sol
sei_json_rpc/tests/contract/IERC20.sol
sei_json_rpc/tests/contract/SimpleStorage.sol
sei_json_rpc/tests/test_diff.py
sei_json_rpc/tests/test_query_rpc.py
sei_json_rpc/tests/test_sei.py
sei_json_rpc/utils/assert_handler.py
sei_json_rpc/utils/compile.py
sei_json_rpc/utils/report_generator.py
sei_json_rpc-0.1.4.dist-info/LICENSE
sei_json_rpc-0.1.4.dist-info/METADATA
sei_json_rpc-0.1.4.dist-info/WHEEL
sei_json_rpc-0.1.4.dist-info/RECORD
